planefigures/__init__.py
planefigures/core.py
planefigures/example.py
planefigures-0.3.0.dist-info/LICENSE
planefigures-0.3.0.dist-info/METADATA
planefigures-0.3.0.dist-info/WHEEL
planefigures-0.3.0.dist-info/top_level.txt
planefigures-0.3.0.dist-info/RECORD
