Metadata-Version: 2.1
Name: planefigures
Version: 0.3.0
Summary: A turtle based package that makes drawing common geometric plane shapes a breeze.
Home-page: https://github.com/OthnielDona/planefigures
Author: Othniel Dona Monote
Author-email: othnieldona@gmail.com
License: UNKNOWN
Platform: UNKNOWN
Classifier: Programming Language :: Python :: 3
Classifier: License :: OSI Approved :: MIT License
Classifier: Operating System :: OS Independent
